VERSION
synapsepay/__init__.py
synapsepay/client.py
synapsepay/apibits/__init__.py
synapsepay/apibits/api_client.py
synapsepay/apibits/api_endpoint.py
synapsepay/apibits/api_list.py
synapsepay/apibits/api_method.py
synapsepay/apibits/api_resource.py
synapsepay/apibits/errors.py
synapsepay/apibits/headers_builder.py
synapsepay/apibits/params_builder.py
synapsepay/apibits/path_builder.py
synapsepay/apibits/requester.py
synapsepay/apibits/version.py
synapsepay/endpoints/__init__.py
synapsepay/endpoints/bank.py
synapsepay/endpoints/bank_mfa_device.py
synapsepay/endpoints/bank_mfa_questions.py
synapsepay/endpoints/bank_status.py
synapsepay/endpoints/card.py
synapsepay/endpoints/deposit.py
synapsepay/endpoints/mass_pay.py
synapsepay/endpoints/order.py
synapsepay/endpoints/user.py
synapsepay/endpoints/wire.py
synapsepay/endpoints/withdrawal.py
synapsepay/resources/__init__.py
synapsepay/resources/bank.py
synapsepay/resources/bank_mfa_device.py
synapsepay/resources/bank_mfa_questions.py
synapsepay/resources/bank_status.py
synapsepay/resources/card.py
synapsepay/resources/deposit.py
synapsepay/resources/mass_pay.py
synapsepay/resources/order.py
synapsepay/resources/user.py
synapsepay/resources/wire.py
synapsepay/resources/withdrawal.py
synapsepay/test/__init__.py
synapsepay/test/test_api_list.py
synapsepay/test/test_api_method.py
synapsepay/test/test_headers_builder.py
synapsepay/test/test_params_builder.py
synapsepay/test/test_path_builder.py
synapsepay/test/test_requester.py
synapsepay-0.0.6.dist-info/DESCRIPTION.rst
synapsepay-0.0.6.dist-info/METADATA
synapsepay-0.0.6.dist-info/metadata.json
synapsepay-0.0.6.dist-info/RECORD
synapsepay-0.0.6.dist-info/top_level.txt
synapsepay-0.0.6.dist-info/WHEEL
