Metadata-Version: 2.0
Name: synapsepay
Version: 0.0.6
Summary: SynapsePay allows you to integrate bank payments into your applications
Home-page: http://api.synapsepay.com/v2.0
Author: SynapsePay
Author-email: hello@synapsepay.com
License: UNKNOWN
Platform: UNKNOWN
Requires-Dist: requests (>=2.7.0)
